vswmc_cli-2.1.0-py3.6-nspkg.pth
vswmc/client.py
vswmc/sockjs.py
vswmc/cli/__init__.py
vswmc/cli/__main__.py
vswmc/cli/cp.py
vswmc/cli/logs.py
vswmc/cli/ls.py
vswmc/cli/models.py
vswmc/cli/products.py
vswmc/cli/ps.py
vswmc/cli/rm.py
vswmc/cli/run.py
vswmc/cli/save.py
vswmc/cli/simulations.py
vswmc/cli/stop.py
vswmc/cli/utils.py
vswmc/core/__init__.py
vswmc/core/auth.py
vswmc/core/exceptions.py
vswmc/core/helpers.py
vswmc_cli-2.1.0.dist-info/LICENSE
vswmc_cli-2.1.0.dist-info/METADATA
vswmc_cli-2.1.0.dist-info/WHEEL
vswmc_cli-2.1.0.dist-info/entry_points.txt
vswmc_cli-2.1.0.dist-info/namespace_packages.txt
vswmc_cli-2.1.0.dist-info/top_level.txt
vswmc_cli-2.1.0.dist-info/RECORD
